Metadata-Version: 2.1
Name: DynamicTalk
Version: 0.0.1
Summary: Explore Netsuite's WSDL and convert Python Dictionaries into Netsuite XML
Home-page: https://gitlab.com/wjwatkinson/dynamictalk
Author: Will Watkinson
Author-email: wjwats4295@gmail.com
License: UNKNOWN
Platform: UNKNOWN
Classifier: Programming Language :: Python :: 3
Classifier: License :: OSI Approved :: MIT License
Classifier: Operating System :: OS Independent
Requires-Python: >=3.6
